app/__init__.py
app/resource/__init__.py
app/resource/log-config.json
app/util/__init__.py
app/util/log_util/__init__.py
app/util/log_util/log_util.py
sit_timeline_logging-0.0.5.dist-info/licenses/LICENCE.txt
sit_timeline_logging-0.0.5.dist-info/METADATA
sit_timeline_logging-0.0.5.dist-info/WHEEL
sit_timeline_logging-0.0.5.dist-info/top_level.txt
sit_timeline_logging-0.0.5.dist-info/RECORD
