Metadata-Version: 2.4
Name: sit-timeline-logging
Version: 0.0.5
Summary: SIT timeline logging package
Author: anusorn.l
Author-email: anusorn.l@somapait.com
Classifier: Programming Language :: Python :: 3.11
Classifier: License :: OSI Approved :: MIT License
Classifier: Operating System :: OS Independent
License-File: LICENCE.txt
Dynamic: author
Dynamic: author-email
Dynamic: classifier
Dynamic: description
Dynamic: description-content-type
Dynamic: license-file
Dynamic: summary
